{"elapsed":"9.827","endpoint-url":"http://maps.communities.gov.uk/geoserver/dclg_inspire/ows?service=WFS&version=1.0.0&request=GetFeature&typeName=dclg_inspire%3AEngland_Green_Belt_2017-18_WGS84&outputFormat=GML3","entry-date":"2023-09-01T00:18:46.040191","request-headers":{"Accept":"*/*","Accept-Encoding":"gzip, deflate","Connection":"keep-alive","User-Agent":"DLUHC Digital Land"},"resource":"0e2cc42c6fcd06aebb3717e9a13cefbaa5a3c6590ba044d8812e25eda3e98ebb","response-headers":{"Access-Control-Allow-Origin":"*","CF-Cache-Status":"DYNAMIC","CF-RAY":"7ff957097c2935a0-DFW","Connection":"keep-alive","Content-Disposition":"inline; filename=features.xml","Content-Encoding":"gzip","Content-Type":"text/xml; subtype=gml/3.1.1","Date":"Fri, 01 Sep 2023 00:19:08 GMT","NEL":"{\"success_fraction\":0,\"report_to\":\"cf-nel\",\"max_age\":604800}","Report-To":"{\"endpoints\":[{\"url\":\"https:\\/\\/a.nel.cloudflare.com\\/report\\/v3?s=cW%2FmSokJrkhFz1IlsdAtg2oVmrWAJCRCxDHS1OcJyfxC92%2BcLv9lBsY0NgYWUP1xrqo4C0I78WeoFFdivpoTs9Njg6R56tV2yPDLf81CeFH4I8OhS0gOmh4QbM1wj%2Bv5tsrHc2pYGVdX\"}],\"group\":\"cf-nel\",\"max_age\":604800}","Server":"cloudflare","Transfer-Encoding":"chunked","X-Frame-Options":"SAMEORIGIN"},"ssl-verify":true,"status":"200"}