{"elapsed":"11.389","endpoint-url":"http://maps.communities.gov.uk/geoserver/dclg_inspire/ows?service=WFS&version=1.0.0&request=GetFeature&typeName=dclg_inspire%3AEngland_Green_Belt_2019-20_WGS84&outputFormat=GML3","entry-date":"2023-08-30T00:17:31.543289","request-headers":{"Accept":"*/*","Accept-Encoding":"gzip, deflate","Connection":"keep-alive","User-Agent":"DLUHC Digital Land"},"resource":"ebf46d50cde4bdd1fec04890e12eebc7158983ab24a7bf33c0469a06cf902552","response-headers":{"Access-Control-Allow-Origin":"*","CF-Cache-Status":"DYNAMIC","CF-RAY":"7fe8d9ed7c9347a5-DFW","Connection":"keep-alive","Content-Disposition":"inline; filename=features.xml","Content-Encoding":"gzip","Content-Type":"text/xml; subtype=gml/3.1.1","Date":"Wed, 30 Aug 2023 00:17:32 GMT","NEL":"{\"success_fraction\":0,\"report_to\":\"cf-nel\",\"max_age\":604800}","Report-To":"{\"endpoints\":[{\"url\":\"https:\\/\\/a.nel.cloudflare.com\\/report\\/v3?s=fpRF8N1tIsVMit%2B%2Fxd9EfTXPdmRBD8i9XEwv1iQfqCxKLdnmhO1bmLpuee846r8wttalDYJI8%2BS6%2Br%2FtXk6Vz2drDNMvr586KEhoYmHpwiUemxtgqJEmy1ARh235WBbQ%2BkEsSQ62ureG\"}],\"group\":\"cf-nel\",\"max_age\":604800}","Server":"cloudflare","Transfer-Encoding":"chunked","X-Frame-Options":"SAMEORIGIN"},"ssl-verify":true,"status":"200"}