{"elapsed":"11.085","endpoint-url":"http://maps.communities.gov.uk/geoserver/dclg_inspire/ows?service=WFS&version=1.0.0&request=GetFeature&typeName=dclg_inspire%3AEngland_Green_Belt_2018-19_WGS84&outputFormat=GML3","entry-date":"2023-11-09T00:17:25.794337","request-headers":{"Accept":"*/*","Accept-Encoding":"gzip, deflate","Connection":"keep-alive","User-Agent":"DLUHC Digital Land"},"resource":"c664927a77fa482d9671464599f0c007218793db3bb68b17e45f3dd8bdb8e85c","response-headers":{"Access-Control-Allow-Origin":"*","CF-Cache-Status":"DYNAMIC","CF-RAY":"8231dfaefda76fec-IAD","Connection":"keep-alive","Content-Disposition":"inline; filename=features.xml","Content-Encoding":"gzip","Content-Type":"text/xml; subtype=gml/3.1.1","Date":"Thu, 09 Nov 2023 00:17:37 GMT","NEL":"{\"success_fraction\":0,\"report_to\":\"cf-nel\",\"max_age\":604800}","Report-To":"{\"endpoints\":[{\"url\":\"https:\\/\\/a.nel.cloudflare.com\\/report\\/v3?s=w4zNQtAqPaYvVjPIemGXsWbalBovsbOKhE1ritG05mD5dJudHsnZ0tWTc%2FWQ8m6m%2FhQrh1Vs0B2wu7r9DZXOVeGOnQmaaAFMKDSTc5nDMoUMcZLwV7N4tNO6HwWp8slxMiVHMiLhmdd%2F\"}],\"group\":\"cf-nel\",\"max_age\":604800}","Server":"cloudflare","Transfer-Encoding":"chunked","X-Frame-Options":"SAMEORIGIN"},"ssl-verify":true,"status":"200"}