{"elapsed":"11.316","endpoint-url":"http://maps.communities.gov.uk/geoserver/dclg_inspire/ows?service=WFS&version=1.0.0&request=GetFeature&typeName=dclg_inspire%3AEngland_Green_Belt_2015-16_WGS84&outputFormat=GML3","entry-date":"2021-12-12T01:06:15.607557","request-headers":{"Accept":"*/*","Accept-Encoding":"gzip, deflate","Connection":"keep-alive","User-Agent":"Digital Land"},"resource":"bcc3680ca22f1e011cf1e1484d62f86f9ddf5d6ebfbd15d2c6a770f56b454440","response-headers":{"Access-Control-Allow-Origin":"*","CF-Cache-Status":"DYNAMIC","CF-RAY":"6bc30d584b8b82b7-IAD","Connection":"keep-alive","Content-Disposition":"inline; filename=features.xml","Content-Encoding":"gzip","Content-Type":"text/xml; subtype=gml/3.1.1","Date":"Sun, 12 Dec 2021 01:06:47 GMT","NEL":"{\"success_fraction\":0,\"report_to\":\"cf-nel\",\"max_age\":604800}","Report-To":"{\"endpoints\":[{\"url\":\"https:\\/\\/a.nel.cloudflare.com\\/report\\/v3?s=UnCUVAX2CFql93GMcv0RLFchHmOkQC6ALAhVoG6KbR10Z1fjnFaiSeuUsCXMNRDbt1AxRHHgviXp95yyxFQs2eZlp5xJsqeX83vA6oRHmgQdv2kME3B1DQfG7gmiVivDNquJiej5zZ6M\"}],\"group\":\"cf-nel\",\"max_age\":604800}","Server":"cloudflare","Transfer-Encoding":"chunked","X-Frame-Options":"SAMEORIGIN"},"ssl-verify":true,"status":"200"}