{"elapsed":"9.606","endpoint-url":"http://maps.communities.gov.uk/geoserver/dclg_inspire/ows?service=WFS&version=1.0.0&request=GetFeature&typeName=dclg_inspire%3AEngland_Green_Belt_2018-19_WGS84&outputFormat=GML3","entry-date":"2023-11-26T00:18:14.238183","request-headers":{"Accept":"*/*","Accept-Encoding":"gzip, deflate","Connection":"keep-alive","User-Agent":"DLUHC Digital Land"},"resource":"c664927a77fa482d9671464599f0c007218793db3bb68b17e45f3dd8bdb8e85c","response-headers":{"Access-Control-Allow-Origin":"*","CF-Cache-Status":"DYNAMIC","CF-RAY":"82bdf434be10585a-IAD","Connection":"keep-alive","Content-Disposition":"inline; filename=features.xml","Content-Encoding":"gzip","Content-Type":"text/xml; subtype=gml/3.1.1","Date":"Sun, 26 Nov 2023 00:18:24 GMT","NEL":"{\"success_fraction\":0,\"report_to\":\"cf-nel\",\"max_age\":604800}","Report-To":"{\"endpoints\":[{\"url\":\"https:\\/\\/a.nel.cloudflare.com\\/report\\/v3?s=m%2FtrkH4nssMDmWUMPzuHcMARRJtkcls8z96R907B%2BfLfPvH7VmLcZwYVMNOd5dUgD%2B%2FBtOXhUR2glV8zOd70bP2TbdW6hjG%2Fh%2FulKI8Dc1GwVvb0IoiTxyHisjUomQ4kZASoUlW76UNt\"}],\"group\":\"cf-nel\",\"max_age\":604800}","Server":"cloudflare","Transfer-Encoding":"chunked","X-Frame-Options":"SAMEORIGIN"},"ssl-verify":true,"status":"200"}